Workbook

Sheet Cover
A1: Microsoft Corporation (MSFT)
A2: DCF Valuation
A3: Company | B3: Microsoft Corporation
A4: Ticker | B4: MSFT
A5: Valuation Method | B5: Discounted Cash Flow (DCF)
A6: Currency | B6: USD
A7: Purpose | B7: Estimate the intrinsic value of Microsoft using a
B8: discounted cash flow valuation.

Sheet Historical Financials
A1: $ in millions | B1: FY2022 | C1: FY2023 | D1: FY2024 | E1: FY2025
A2: Revenue | B2: 198270 | C2: 211915 | D2: 245122 | E2: 281724
A3: Operating Income | B3: 83383 | C3: 88523 | D3: 109433 | E3: 128528
A4: D&A | B4: 13775 | C4: 13861 | D4: 22287 | E4: 34153
A5: CapEx | B5: 23886 | C5: 28107 | D5: 44477 | E5: 64551
A6: Tax Expense | B6: 10978 | C6: 16950 | D6: 19651 | E6: 21795
A7: Working Capital build
A8: Operating current assets
A9: Accounts recievable | D9: 56924 | E9: 69905
A10: Inventory | D10: 1246 | E10: 938
A11: Other current assets | D11: 26021 | E11: 25723
A12: Operating current liabilities
A13: Accounts payable | D13: 21996 | E13: 27724
A14: Unearned revenue | D14: 57582 | E14: 64555
A15: Other current liabilities | D15: 19185 | E15: 25020
A16: Net working capital | D16: =SUM(D9:D11)-SUM(D13:D15) -> -14572 | E16: =SUM(E9:E11)-SUM(E13:E15) -> -20733

Sheet Forecast
A1: $ in millions | B1: FY2026 | C1: FY2027 | D1: FY2028 | E1: FY2029 | F1: FY2030
A2: Revenue | B2: ='Historical Financials'!E2*(1+B3) -> 315530.88 | C2: =B2*(1+C3) -> 350239.28 | D2: =C2*(1+D3) -> 385263.2 | E2: =D2*(1+E3) -> 419936.89 | F2: =E2*(1+F3) -> 453531.84
A3: Revenue Growth | B3: 0.12 | C3: 0.11 | D3: 0.1 | E3: 0.09 | F3: 0.08
A4: EBITDA | B4: =B2*B5 -> 183007.91 | C4: =C2*C5 -> 206641.17 | D4: =D2*D5 -> 231157.92 | E4: =E2*E5 -> 256161.5 | F4: =F2*F5 -> 281189.74
A5: EBITDA Margin | B5: 0.58 | C5: 0.59 | D5: 0.6 | E5: 0.61 | F5: 0.62
A6: D&A | B6: =B2*12.1% -> 38179.236 | C6: =C2*12.1% -> 42378.952 | D6: =D2*12.1% -> 46616.848 | E6: =E2*12.1% -> 50812.364 | F6: =F2*12.1% -> 54877.353
A7: EBIT | B7: =B4-B6 -> 144828.67 | C7: =C4-C6 -> 164262.22 | D7: =D4-D6 -> 184541.07 | E7: =E4-E6 -> 205349.14 | F7: =F4-F6 -> 226312.39
A8: Tax rate | B8: 0.175 | C8: 0.175 | D8: 0.175 | E8: 0.175 | F8: 0.175
A9: Tax on EBIT | B9: =B7*B8 -> 25345.018 | C9: =C7*C8 -> 28745.889 | D9: =D7*D8 -> 32294.688 | E9: =E7*E8 -> 35936.1 | F9: =F7*F8 -> 39604.668
A10: NOPAT | B10: =B7-B9 -> 119483.66 | C10: =C7-C9 -> 135516.33 | D10: =D7-D9 -> 152246.39 | E10: =E7-E9 -> 169413.04 | F10: =F7-F9 -> 186707.72
A11: CapEx | B11: =B2*22.9% -> 72256.572 | C11: =C2*22.9% -> 80204.794 | D11: =D2*22.9% -> 88225.274 | E11: =E2*22.9% -> 96165.548 | F11: =F2*22.9% -> 103858.79
A12: NWC | B12: =B2*(-7.36%) -> -23223.073 | C12: =C2*(-7.36%) -> -25777.611 | D12: =D2*(-7.36%) -> -28355.372 | E12: =E2*(-7.36%) -> -30907.355 | F12: =F2*(-7.36%) -> -33379.944
A13: Change in NWC | B13: =B12-'Historical Financials'!E16 -> -2490.0728 | C13: =C12-B12 -> -2554.538 | D13: =D12-C12 -> -2577.7611 | E13: =E12-D12 -> -2551.9835 | F13: =F12-E12 -> -2472.5884
A14: Free Cash Flow | B14: =B10+B6-B11-B13 -> 87896.394 | C14: =C10+C6-C11-C13 -> 100245.03 | D14: =D10+D6-D11-D13 -> 113215.72 | E14: =E10+E6-E11-E13 -> 126611.84 | F14: =F10+F6-F11-F13 -> 140198.87

Sheet WACC
A1: WACC Calculation
A2: Risk-free rate | B2: 0.0477
A3: Beta | B3: 1
A4: Equity risk premium | B4: 0.045
A5: Cost of equity | B5: =B2+B3*B4 -> 0.0927
A6: Pre-tax cost of Debt | B6: 0.035
A7: Tax rate | B7: 0.175
A8: After-tax cost of debt | B8: =B6*(1-B7) -> 0.028875
A9: Market value of equity | B9: 3823000
A10: Debt | B10: 40294
A11: Totalcapital | B11: =B9+B10 -> 3863294
A12: Equity weight | B12: =B9/B11 -> 0.98957004
A13: Debt weight | B13: =B10/B11 -> 0.01042996
A14: WACC | B14: =B12*B5+B13*B8 -> 0.092034308

Sheet DCF Valuation
A1: DCF Valuation
A2: $ in millions | B2: FY2026 | C2: FY2027 | D2: FY2028 | E2: FY2029 | F2: FY2030
A3: Free cash flow | B3: =Forecast!B14 -> 87896.394 | C3: =Forecast!C14 -> 100245.03 | D3: =Forecast!D14 -> 113215.72 | E3: =Forecast!E14 -> 126611.84 | F3: =Forecast!F14 -> 140198.87
A4: Discount period | B4: 1 | C4: 2 | D4: 3 | E4: 4 | F4: 5
A5: Discount Factor | B5: =1/(1+WACC!$B$14)^B4 -> 0.91572215 | C5: =1/(1+WACC!$B$14)^C4 -> 0.83854705 | D5: =1/(1+WACC!$B$14)^D4 -> 0.7678761 | E5: =1/(1+WACC!$B$14)^E4 -> 0.70316115 | F5: =1/(1+WACC!$B$14)^F4 -> 0.64390024
A6: Present value of FCF | B6: =B3*B5 -> 80488.674 | C6: =C3*C5 -> 84060.173 | D6: =D3*D5 -> 86935.647 | E6: =E3*E5 -> 89028.527 | F6: =F3*F5 -> 90274.087
A8: Terminal value
A9: Terminal growth rate | B9: 0.03
A10: FY2030 FCF | B10: =F3 -> 140198.87
A11: FY2031 FCF | B11: =B10*(1+B9) -> 144404.84
A12: Terminal value | B12: =B11/(WACC!$B$14-B9) -> 2327822.2
A13: PV of terminal value | B13: =B12*F5 -> 1498885.3
A15: DCF Valuation Summary
A16: PV of Forecast FCF | B16: =SUM(B6:F6) -> 430787.11
A17: PV of Terminal Value | B17: =B13 -> 1498885.3
A18: Enterprise value | B18: =B16+B17 -> 1929672.4
A20: Equity value bridge
A21: Enterprise value | B21: =B18 -> 1929672.4
A22: Cash & short term investment | B22: 76843
A23: Debt | B23: 40294
A24: Equity value | B24: =B21+B22-B23 -> 1966221.4
A25: Shares outstanding | B25: 7427
A26: Implied Share price | B26: =B24/B25 -> 264.73965
A28: Valuation Summary
A29: WACC | B29: =WACC!B14 -> 0.092034308
A30: Terminal growth rate | B30: =B9 -> 0.03
A31: Enterprise value | B31: =B18 -> 1929672.4
A32: Equity value | B32: =B24 -> 1966221.4
A33: Implied share price | B33: =B26 -> 264.73965
A35: Assumption | B35: Value
A36: WACC | B36: 0.092
A37: Terminal Growth | B37: 0.03
A38: Valuation Method | B38: DCF
A39: Forecast Period | B39: 2026-2030

Sheet Sensitivity
A1: Implied Share Price | B1: 264.74
A2: WACC / Terminal Growth | B2: 0.02 | C2: 0.025 | D2: 0.03 | E2: 0.035 | F2: 0.04
A3: 0.08 | B3: =('DCF Valuation'!$B$16+('DCF Valuation'!$F$3*(1+B$2)/(($A3)-B$2))*'DCF Valuation'!$F$5+'DCF Valuation'!$B$22-'DCF Valuation'!$B$23)/'DCF Valuation'!$B$25 -> 269.55643 | C3: =('DCF Valuation'!$B$16+('DCF Valuation'!$F$3*(1+C$2)/(($A3)-C$2))*'DCF Valuation'!$F$5+'DCF Valuation'!$B$22-'DCF Valuation'!$B$23)/'DCF Valuation'!$B$25 -> 289.44619 | D3: =('DCF Valuation'!$B$16+('DCF Valuation'!$F$3*(1+D$2)/(($A3)-D$2))*'DCF Valuation'!$F$5+'DCF Valuation'!$B$22-'DCF Valuation'!$B$23)/'DCF Valuation'!$B$25 -> 313.3139 | E3: =('DCF Valuation'!$B$16+('DCF Valuation'!$F$3*(1+E$2)/(($A3)-E$2))*'DCF Valuation'!$F$5+'DCF Valuation'!$B$22-'DCF Valuation'!$B$23)/'DCF Valuation'!$B$25 -> 342.48554 | F3: =('DCF Valuation'!$B$16+('DCF Valuation'!$F$3*(1+F$2)/(($A3)-F$2))*'DCF Valuation'!$F$5+'DCF Valuation'!$B$22-'DCF Valuation'!$B$23)/'DCF Valuation'!$B$25 -> 378.9501
A4: 0.085 | B4: =('DCF Valuation'!$B$16+('DCF Valuation'!$F$3*(1+B$2)/(($A4)-B$2))*'DCF Valuation'!$F$5+'DCF Valuation'!$B$22-'DCF Valuation'!$B$23)/'DCF Valuation'!$B$25 -> 253.66162 | C4: =('DCF Valuation'!$B$16+('DCF Valuation'!$F$3*(1+C$2)/(($A4)-C$2))*'DCF Valuation'!$F$5+'DCF Valuation'!$B$22-'DCF Valuation'!$B$23)/'DCF Valuation'!$B$25 -> 270.56933 | D4: =('DCF Valuation'!$B$16+('DCF Valuation'!$F$3*(1+D$2)/(($A4)-D$2))*'DCF Valuation'!$F$5+'DCF Valuation'!$B$22-'DCF Valuation'!$B$23)/'DCF Valuation'!$B$25 -> 290.55117 | E4: =('DCF Valuation'!$B$16+('DCF Valuation'!$F$3*(1+E$2)/(($A4)-E$2))*'DCF Valuation'!$F$5+'DCF Valuation'!$B$22-'DCF Valuation'!$B$23)/'DCF Valuation'!$B$25 -> 314.52938 | F4: =('DCF Valuation'!$B$16+('DCF Valuation'!$F$3*(1+F$2)/(($A4)-F$2))*'DCF Valuation'!$F$5+'DCF Valuation'!$B$22-'DCF Valuation'!$B$23)/'DCF Valuation'!$B$25 -> 343.83608
A5: 0.09 | B5: =('DCF Valuation'!$B$16+('DCF Valuation'!$F$3*(1+B$2)/(($A5)-B$2))*'DCF Valuation'!$F$5+'DCF Valuation'!$B$22-'DCF Valuation'!$B$23)/'DCF Valuation'!$B$25 -> 240.0375 | C5: =('DCF Valuation'!$B$16+('DCF Valuation'!$F$3*(1+C$2)/(($A5)-C$2))*'DCF Valuation'!$F$5+'DCF Valuation'!$B$22-'DCF Valuation'!$B$23)/'DCF Valuation'!$B$25 -> 254.59661 | D5: =('DCF Valuation'!$B$16+('DCF Valuation'!$F$3*(1+D$2)/(($A5)-D$2))*'DCF Valuation'!$F$5+'DCF Valuation'!$B$22-'DCF Valuation'!$B$23)/'DCF Valuation'!$B$25 -> 271.58224 | E5: =('DCF Valuation'!$B$16+('DCF Valuation'!$F$3*(1+E$2)/(($A5)-E$2))*'DCF Valuation'!$F$5+'DCF Valuation'!$B$22-'DCF Valuation'!$B$23)/'DCF Valuation'!$B$25 -> 291.65616 | F5: =('DCF Valuation'!$B$16+('DCF Valuation'!$F$3*(1+F$2)/(($A5)-F$2))*'DCF Valuation'!$F$5+'DCF Valuation'!$B$22-'DCF Valuation'!$B$23)/'DCF Valuation'!$B$25 -> 315.74487
A6: 0.095 | B6: =('DCF Valuation'!$B$16+('DCF Valuation'!$F$3*(1+B$2)/(($A6)-B$2))*'DCF Valuation'!$F$5+'DCF Valuation'!$B$22-'DCF Valuation'!$B$23)/'DCF Valuation'!$B$25 -> 228.22993 | C6: =('DCF Valuation'!$B$16+('DCF Valuation'!$F$3*(1+C$2)/(($A6)-C$2))*'DCF Valuation'!$F$5+'DCF Valuation'!$B$22-'DCF Valuation'!$B$23)/'DCF Valuation'!$B$25 -> 240.9057 | D6: =('DCF Valuation'!$B$16+('DCF Valuation'!$F$3*(1+D$2)/(($A6)-D$2))*'DCF Valuation'!$F$5+'DCF Valuation'!$B$22-'DCF Valuation'!$B$23)/'DCF Valuation'!$B$25 -> 255.5316 | E6: =('DCF Valuation'!$B$16+('DCF Valuation'!$F$3*(1+E$2)/(($A6)-E$2))*'DCF Valuation'!$F$5+'DCF Valuation'!$B$22-'DCF Valuation'!$B$23)/'DCF Valuation'!$B$25 -> 272.59514 | F6: =('DCF Valuation'!$B$16+('DCF Valuation'!$F$3*(1+F$2)/(($A6)-F$2))*'DCF Valuation'!$F$5+'DCF Valuation'!$B$22-'DCF Valuation'!$B$23)/'DCF Valuation'!$B$25 -> 292.76115
A7: 0.1 | B7: =('DCF Valuation'!$B$16+('DCF Valuation'!$F$3*(1+B$2)/(($A7)-B$2))*'DCF Valuation'!$F$5+'DCF Valuation'!$B$22-'DCF Valuation'!$B$23)/'DCF Valuation'!$B$25 -> 217.89831 | C7: =('DCF Valuation'!$B$16+('DCF Valuation'!$F$3*(1+C$2)/(($A7)-C$2))*'DCF Valuation'!$F$5+'DCF Valuation'!$B$22-'DCF Valuation'!$B$23)/'DCF Valuation'!$B$25 -> 229.04025 | D7: =('DCF Valuation'!$B$16+('DCF Valuation'!$F$3*(1+D$2)/(($A7)-D$2))*'DCF Valuation'!$F$5+'DCF Valuation'!$B$22-'DCF Valuation'!$B$23)/'DCF Valuation'!$B$25 -> 241.77391 | E7: =('DCF Valuation'!$B$16+('DCF Valuation'!$F$3*(1+E$2)/(($A7)-E$2))*'DCF Valuation'!$F$5+'DCF Valuation'!$B$22-'DCF Valuation'!$B$23)/'DCF Valuation'!$B$25 -> 256.46659 | F7: =('DCF Valuation'!$B$16+('DCF Valuation'!$F$3*(1+F$2)/(($A7)-F$2))*'DCF Valuation'!$F$5+'DCF Valuation'!$B$22-'DCF Valuation'!$B$23)/'DCF Valuation'!$B$25 -> 273.60804
